kwe/__init__.py
kwe/base.py
kwe/constant.py
kwe/eda.py
kwe/models/__init__.py
kwe/models/graph.py
kwe/models/nn.py
kwe/models/statistics.py
kwe/process.py
kwe-0.1.5.dist-info/METADATA
kwe-0.1.5.dist-info/WHEEL
kwe-0.1.5.dist-info/RECORD
