Metadata-Version: 2.1
Name: kwe
Version: 0.1.5
Summary: 
Author: 윤성민
Author-email: meetingstranger@gmail.com
Requires-Python: >=3.10,<3.11
Classifier: Programming Language :: Python :: 3
Classifier: Programming Language :: Python :: 3.10
Requires-Dist: datasets (>=2.18.0,<3.0.0)
Requires-Dist: gensim (>=4.3.2,<5.0.0)
Requires-Dist: keybert (>=0.8.4,<0.9.0)
Requires-Dist: nltk (>=3.8.1,<4.0.0)
Requires-Dist: scipy (==1.10.1)
